SurfaceDefects/SurfaceDefects.py
SurfaceDefects/__init__.py
SurfaceDefects1/SurfaceDefects1.py
SurfaceDefects-1.0.0.dist-info/LICENSE.txt
SurfaceDefects-1.0.0.dist-info/METADATA
SurfaceDefects-1.0.0.dist-info/WHEEL
SurfaceDefects-1.0.0.dist-info/top_level.txt
SurfaceDefects-1.0.0.dist-info/RECORD
