Metadata-Version: 2.1
Name: SurfaceDefects
Version: 1.0.0
Summary: A package for detecting and analysing defects/pores in concrete, steel or similar surfaces.
Author-email: Amir Hamza <19pwciv5384@uetpeshawar.edu.pk>
Project-URL: Homepage, https://github.com/engr-amir-hamza/SurfaceDefects.git
Project-URL: Bug Tracker, https://github.com/engr-amir-hamza/SurfaceDefects/issues
Keywords: Computer Vision,Contours,Pores Detection in concrete,Pores Detection in Steel
Classifier: Programming Language :: Python :: 3
Classifier: License :: OSI Approved :: MIT License
Classifier: Operating System :: OS Independent
Requires-Python: >=3.7
License-File: LICENSE.txt
